uranium_plus/__init__.py
uranium_plus-2.1.1.dist-info/METADATA
uranium_plus-2.1.1.dist-info/WHEEL
uranium_plus-2.1.1.dist-info/top_level.txt
uranium_plus-2.1.1.dist-info/RECORD
