Metadata-Version: 2.1
Name: uranium-plus
Version: 2.1.1
Summary: an opinionated base package for builds using uranium
Home-page: http://uranium.readthedocs.org
Author: Yusuke Tsutsumi
Author-email: yusuke@tsutsumi.io
License: UNKNOWN
Platform: UNKNOWN
Classifier: Development Status :: 4 - Beta
Classifier: Operating System :: MacOS
Classifier: Operating System :: POSIX :: Linux
Classifier: Topic :: System :: Software Distribution
Classifier: License :: OSI Approved :: MIT License
Classifier: Programming Language :: Python
Classifier: Programming Language :: Python :: 2
Classifier: Programming Language :: Python :: 3
Requires-Dist: Babel
Requires-Dist: Sphinx
Requires-Dist: sphinx-rtd-theme
Requires-Dist: pytest
Requires-Dist: pytest-cov
Requires-Dist: wheel
Requires-Dist: twine
Provides-Extra: vscode
Requires-Dist: pylint ; extra == 'vscode'
Requires-Dist: rope ; extra == 'vscode'
Requires-Dist: black ; (python_version >= "3.6") and extra == 'vscode'
